{
  "username": "@dotfn",
  "name": "Nicolás Jiménez",
  "bio": "Frontend Developer · Producto Digital · Diseño UX/UI",
  "avatar": "/contact-profile.jpg",
  "featuredImage": "/background.jpg",
  "links": [
    {
      "label": "Curriculum Vitae",
      "url": "/cv",
      "icon": "cv",
      "description": "Versión web interactiva & PDF"
    },
    {
      "label": "LinkedIn",
      "url": "https://www.linkedin.com/in/dotfn",
      "icon": "in",
      "description": "Perfil profesional"
    },
    {
      "label": "GitHub",
      "url": "https://github.com/dotfn",
      "icon": "gh",
      "description": "Repositorios & proyectos"
    },
    {
      "label": "X (Twitter)",
      "url": "https://x.com/dotfn_",
      "icon": "x",
      "description": "Pensamientos & tecnología"
    },
    {
      "label": "Sitio Web",
      "url": "https://dotfn.dev",
      "icon": "pf",
      "description": "Portafolio & Blog"
    },
    {
      "label": "Email",
      "url": "mailto:dotfn.contact@gmail.com",
      "icon": "em",
      "description": "Escribime directo"
    }
  ],
  "footer": "Sitio en construcción · Volvé pronto"
}